setup.py
distributions/Binomialdistribution.py
distributions/Gaussiandistribution.py
distributions/Generaldistribution.py
distributions/__init__.py
weisurya_gaussian_distribution.egg-info/PKG-INFO
weisurya_gaussian_distribution.egg-info/SOURCES.txt
weisurya_gaussian_distribution.egg-info/dependency_links.txt
weisurya_gaussian_distribution.egg-info/not-zip-safe
weisurya_gaussian_distribution.egg-info/top_level.txt