Metadata-Version: 1.0
Name: weisurya-gaussian-distribution
Version: 0.1
Summary: Gaussian distributions by weisurya
Home-page: UNKNOWN
Author: UNKNOWN
Author-email: UNKNOWN
License: UNKNOWN
Platform: UNKNOWN
